nvncli/__init__.py
nvncli/cli.py
nvncli/multihost.py
nvncli/nvn_utils.py
nvncli/spider.py
nvncli/update_content.py
nvnc-0.1.5.dist-info/LICENSE
nvnc-0.1.5.dist-info/METADATA
nvnc-0.1.5.dist-info/WHEEL
nvnc-0.1.5.dist-info/entry_points.txt
nvnc-0.1.5.dist-info/top_level.txt
nvnc-0.1.5.dist-info/RECORD
